workflow4ds/__init__.py
workflow4ds/decorators.py
workflow4ds/img_dict.npy
workflow4ds/logger.py
workflow4ds/settings.py
workflow4ds/tunnels.py
workflow4ds/utils.py
workflow4ds/database/__init__.py
workflow4ds/database/doris.py
workflow4ds/database/oracle.py
workflow4ds/database/compat/sqlalchemy/__init__.py
workflow4ds/database/compat/sqlalchemy/datatype.py
workflow4ds/database/compat/sqlalchemy/dialect.py
workflow4ds/hive/__init__.py
workflow4ds/hive/api.py
workflow4ds/hive/compat.py
workflow4ds/hue/__init__.py
workflow4ds/hue/hue.py
workflow4ds/hue/hue_download.py
workflow4ds/jump_server/__init__.py
workflow4ds/jump_server/tunnels.py
workflow4ds/jupyter/__init__.py
workflow4ds/jupyter/base.py
workflow4ds/jupyter/mem_usage.py
workflow4ds/model_validate/__init__.py
workflow4ds/model_validate/metrics.py
workflow4ds/model_validate/reports.py
workflow4ds/zeppelin/__init__.py
workflow4ds/zeppelin/base.py
workflow4ds-0.2.11.dist-info/LICENSE
workflow4ds-0.2.11.dist-info/METADATA
workflow4ds-0.2.11.dist-info/WHEEL
workflow4ds-0.2.11.dist-info/top_level.txt
workflow4ds-0.2.11.dist-info/RECORD
