Metadata-Version: 2.2
Name: workflow4ds
Version: 0.2.11
Summary: Data Pipeline Integration for Data Scientists
Author-email: Allen Li <supermrli@hotmail.com>
Project-URL: Homepage, https://github.com/allen-li1231/workflow
Project-URL: Issues, https://github.com/allen-li1231/workflow/issues
Classifier: Programming Language :: Python :: 3
Classifier: License :: OSI Approved :: MIT License
Classifier: Operating System :: OS Independent
Requires-Python: >=2.7
License-File: LICENSE
Requires-Dist: requests
Requires-Dist: tqdm
Requires-Dist: openpyxl
Requires-Dist: pandas
Provides-Extra: hive
Requires-Dist: impyla; extra == "hive"
Provides-Extra: hue
Requires-Dist: requests_toolbelt; extra == "hue"
Provides-Extra: tunnel
Requires-Dist: paramiko; extra == "tunnel"
Provides-Extra: oracle
Requires-Dist: cx_Oracle; extra == "oracle"
Provides-Extra: doris
Requires-Dist: sqlalchemy>=2.0.0; extra == "doris"
Provides-Extra: all
Requires-Dist: workflow4ds[doris,hive,hue,oracle,tunnel]; extra == "all"
